{
  "category": "help_requests",
  "items": [
    {
      "ru": "Помоги!",
      "ing": "Г1о де!",
      "pron": "g1o de"
    },
    {
      "ru": "Мне нужна помощь",
      "ing": "Сун г1о де дез",
      "pron": "sun guo de dez"
    },
    {
      "ru": "Позови кого-нибудь",
      "ing": "Хьанца ца веза!",
      "pron": "khantsa tsa vezza"
    },
    {
      "ru": "Помоги ему",
      "ing": "Из г1о деда",
      "pron": "iz g1o deda"
    },
    {
      "ru": "Помоги мне",
      "ing": "Са г1о де",
      "pron": "sa g1o de"
    },
    {
      "ru": "Помоги им",
      "ing": "Оха г1о деда",
      "pron": "okha g1o deda"
    },
    {
      "ru": "Позвони",
      "ing": "Телефон деш!",
      "pron": "telefon desh"
    },
    {
      "ru": "Вызови помощь",
      "ing": "Г1о ца веза",
      "pron": "g1o tsa vezza"
    },
    {
      "ru": "Я потерялся",
      "ing": "Со седа хинна",
      "pron": "so seda khinna"
    },
    {
      "ru": "Я поранился",
      "ing": "Со беха хинна",
      "pron": "so bekha khinna"
    },
    {
      "ru": "Поддержи меня",
      "ing": "Са дог1ийла",
      "pron": "sa dog1iyla"
    },
    {
      "ru": "Подожди меня",
      "ing": "Са сабар де",
      "pron": "sa sabar de"
    },
    {
      "ru": "Жди здесь",
      "ing": "Хьокха сабар де",
      "pron": "khyokha sabar de"
    }
  ]
}